[
  {
    "name": "Air Max 97 (Japan Exclusive)",
    "images": [
      "https://res.cloudinary.com/dvpfyxknb/image/upload/v1780155255/r8ypyehq36jg7l0x9yxx.jpg",
      "https://res.cloudinary.com/dvpfyxknb/image/upload/v1780155255/zq3ncmd7pgpraebj9uam.jpg",
      "https://res.cloudinary.com/dvpfyxknb/image/upload/v1780155255/hpevsesewjh01szigawt.jpg",
      "https://res.cloudinary.com/dvpfyxknb/image/upload/v1780155255/yajgjkaz9h97rzzdnbmc.jpg",
      "https://res.cloudinary.com/dvpfyxknb/image/upload/v1780155255/mudb5byhxbh11aw1tp3z.jpg"
    ],
    "sizes": [],
    "stock": 45,
    "price": "₱5,200",
    "variants": {
      "Red": {
        "sizes": [
          "6",
          "7",
          "8",
          "9",
          "10",
          "11",
          "12",
          "One Size",
          "Free Size"
        ],
        "stock": {
          "6": 4,
          "7": 5,
          "8": 5,
          "9": 5,
          "10": 5,
          "11": 5,
          "12": 5,
          "Free Size": 5,
          "One Size": 5
        }
      }
    },
    "id": 16,
    "category2": "Nike",
    "deposit": "500",
    "color": "Black",
    "available": true,
    "category1": "Shoes",
    "category0": "MENS",
    "description": "test"
  },
  {
    "name": "Dunk High Retro",
    "sizes": [],
    "images": [
      "images/products/placeholder.svg"
    ],
    "stock": 8,
    "price": "₱497",
    "variants": {
      "Default": {
        "stock": {
          "q": 8
        }
      }
    },
    "id": 17,
    "category2": "Adidas",
    "color": "White",
    "category1": "Shoes",
    "available": true,
    "category0": "MENS",
    "description": "Authentic Japanese shoes from Adidas. Limited Japan-exclusive item."
  },
  {
    "price": "₱614",
    "stock": 15,
    "images": [
      "images/products/placeholder.svg"
    ],
    "sizes": [],
    "name": "Air Jordan 1 Low",
    "description": "Authentic Japanese shoes from New Balance. Limited Japan-exclusive item.",
    "available": true,
    "category1": "Shoes",
    "category0": "MENS",
    "color": "Beige",
    "category2": "New Balance",
    "id": 18,
    "variants": {
      "Default": {
        "stock": {
          "q": 15
        }
      }
    }
  },
  {
    "color": "Beige",
    "category2": "Uniqlo",
    "description": "Authentic Japanese clothing from Uniqlo. Limited Japan-exclusive item.",
    "category1": "Clothing",
    "available": true,
    "category0": "MENS",
    "id": 19,
    "variants": {
      "Default": {
        "stock": {
          "q": 22
        }
      }
    },
    "price": "₱731",
    "images": [
      "images/products/placeholder.svg"
    ],
    "sizes": [],
    "name": "Blazer Mid '77",
    "stock": 22
  },
  {
    "price": "₱848",
    "stock": 29,
    "name": "Air Force 1 Mid",
    "images": [
      "images/products/placeholder.svg"
    ],
    "sizes": [],
    "category0": "MENS",
    "available": true,
    "category1": "Clothing",
    "description": "Authentic Japanese clothing from GU. Limited Japan-exclusive item.",
    "category2": "GU",
    "color": "Black",
    "variants": {
      "Default": {
        "stock": {
          "q": 29
        }
      }
    },
    "id": 20
  },
  {
    "variants": {
      "Default": {
        "stock": {
          "q": 36
        }
      }
    },
    "id": 21,
    "category2": "Supreme",
    "color": "White",
    "available": true,
    "category1": "Clothing",
    "category0": "MENS",
    "description": "Authentic Japanese clothing from Supreme. Limited Japan-exclusive item.",
    "name": "Ultraboost 22",
    "sizes": [],
    "images": [
      "images/products/placeholder.svg"
    ],
    "stock": 36,
    "price": "₱965"
  },
  {
    "stock": 43,
    "name": "NMD_R1 Primeknit",
    "images": [
      "images/products/placeholder.svg"
    ],
    "sizes": [],
    "price": "₱1082",
    "variants": {
      "Default": {
        "stock": {
          "q": 43
        }
      }
    },
    "id": 22,
    "category0": "MENS",
    "category1": "Shoes",
    "available": true,
    "description": "Authentic Japanese shoes from Nike. Limited Japan-exclusive item.",
    "category2": "Nike",
    "color": "Pink"
  },
  {
    "price": "₱1199",
    "images": [
      "images/products/placeholder.svg"
    ],
    "sizes": [],
    "name": "Superstar (Japan Edition)",
    "stock": 50,
    "color": "Pink",
    "category2": "Adidas",
    "description": "Authentic Japanese shoes from Adidas. Limited Japan-exclusive item.",
    "available": true,
    "category1": "Shoes",
    "category0": "MENS",
    "id": 23,
    "variants": {
      "Default": {
        "stock": {
          "q": 50
        }
      }
    }
  },
  {
    "price": "₱1316",
    "stock": 7,
    "name": "Gazelle (Made in Japan)",
    "images": [
      "images/products/placeholder.svg"
    ],
    "sizes": [],
    "category0": "MENS",
    "available": true,
    "category1": "Clothing",
    "description": "Authentic Japanese clothing from Uniqlo. Limited Japan-exclusive item.",
    "category2": "Uniqlo",
    "color": "White",
    "variants": {
      "Default": {
        "stock": {
          "q": 7
        }
      }
    },
    "id": 24
  },
  {
    "price": "₱1433",
    "stock": 14,
    "sizes": [],
    "images": [
      "images/products/placeholder.svg"
    ],
    "name": "Forum Low",
    "description": "Authentic Japanese clothing from GU. Limited Japan-exclusive item.",
    "category1": "Clothing",
    "available": true,
    "category0": "MENS",
    "color": "Pink",
    "category2": "GU",
    "id": 25,
    "variants": {
      "Default": {
        "stock": {
          "q": 14
        }
      }
    }
  },
  {
    "price": "₱1550",
    "images": [
      "images/products/placeholder.svg"
    ],
    "sizes": [],
    "name": "550 (Japan Exclusive)",
    "stock": 21,
    "color": "",
    "category2": "Shiseido",
    "description": "Authentic Japanese cosmetics from Shiseido. Limited Japan-exclusive item.",
    "category0": "WOMENS",
    "available": false,
    "category1": "Cosmetics",
    "id": 26,
    "variants": {
      "Default": {
        "stock": {
          "q": 21
        }
      }
    }
  },
  {
    "price": "₱1667",
    "stock": 28,
    "name": "574 Classic",
    "sizes": [],
    "images": [
      "images/products/placeholder.svg"
    ],
    "category0": "WOMENS",
    "category1": "Cosmetics",
    "available": true,
    "description": "Authentic Japanese cosmetics from SK-II. Limited Japan-exclusive item.",
    "category2": "SK-II",
    "color": "",
    "variants": {
      "Default": {
        "stock": {
          "q": 28
        }
      }
    },
    "id": 27
  },
  {
    "variants": {
      "Default": {
        "stock": {
          "q": 35
        }
      }
    },
    "id": 28,
    "category2": "G-Shock",
    "color": "Red",
    "category0": "MENS",
    "available": true,
    "category1": "Accessories",
    "description": "Authentic Japanese accessories from G-Shock. Limited Japan-exclusive item.",
    "name": "990v5 Made in Japan",
    "sizes": [],
    "images": [
      "images/products/placeholder.svg"
    ],
    "stock": 35,
    "price": "₱1784"
  },
  {
    "category2": "Lily Brown",
    "color": "Silver",
    "available": true,
    "category1": "Accessories",
    "category0": "MENS",
    "description": "Authentic Japanese accessories from Lily Brown. Limited Japan-exclusive item.",
    "variants": {
      "Default": {
        "stock": {
          "q": 42
        }
      }
    },
    "id": 29,
    "price": "₱1901",
    "name": "U9060",
    "sizes": [],
    "images": [
      "images/products/placeholder.svg"
    ],
    "stock": 42
  },
  {
    "price": "₱2018",
    "images": [
      "images/products/placeholder.svg"
    ],
    "sizes": [],
    "name": "Bape STA Low",
    "stock": 49,
    "color": "Grey",
    "category2": "WTAPS",
    "description": "Authentic Japanese clothing from WTAPS. Limited Japan-exclusive item.",
    "available": true,
    "category1": "Clothing",
    "category0": "MENS",
    "id": 30,
    "variants": {
      "Default": {
        "stock": {
          "q": 49
        }
      }
    }
  },
  {
    "price": "₱2135",
    "images": [
      "images/products/placeholder.svg"
    ],
    "sizes": [],
    "name": "AIRism Cotton T-Shirt",
    "stock": 6,
    "color": "Black",
    "category2": "Undercover",
    "description": "Authentic Japanese clothing from Undercover. Limited Japan-exclusive item.",
    "category0": "MENS",
    "available": true,
    "category1": "Clothing",
    "id": 31,
    "variants": {
      "Default": {
        "stock": {
          "q": 6
        }
      }
    }
  },
  {
    "price": "₱2252",
    "stock": 13,
    "images": [
      "images/products/placeholder.svg"
    ],
    "sizes": [],
    "name": "Supima Cotton Oversized Tee",
    "description": "Authentic Japanese cosmetics from Canmake. Limited Japan-exclusive item.",
    "available": true,
    "category1": "Cosmetics",
    "category0": "WOMENS",
    "color": "",
    "category2": "Canmake",
    "id": 32,
    "variants": {
      "Default": {
        "stock": {
          "q": 13
        }
      }
    }
  },
  {
    "description": "Authentic Japanese cosmetics from Kiss Me. Limited Japan-exclusive item.",
    "category0": "WOMENS",
    "category1": "Cosmetics",
    "available": true,
    "color": "",
    "category2": "Kiss Me",
    "id": 33,
    "variants": {
      "Default": {
        "stock": {
          "q": 20
        }
      }
    },
    "price": "₱2369",
    "stock": 20,
    "sizes": [],
    "images": [
      "images/products/placeholder.svg"
    ],
    "name": "Blocktech Parka"
  },
  {
    "description": "Authentic Japanese shoes from Nike. Limited Japan-exclusive item.",
    "available": true,
    "category1": "Shoes",
    "category0": "MENS",
    "color": "Blue",
    "category2": "Nike",
    "id": 34,
    "variants": {
      "Default": {
        "stock": {
          "q": 27
        }
      }
    },
    "price": "₱2486",
    "stock": 27,
    "sizes": [],
    "images": [
      "images/products/placeholder.svg"
    ],
    "name": "Ultra Light Down Vest"
  },
  {
    "color": "White",
    "category2": "Adidas",
    "description": "Authentic Japanese shoes from Adidas. Limited Japan-exclusive item.",
    "category0": "MENS",
    "available": true,
    "category1": "Shoes",
    "id": 35,
    "variants": {
      "Default": {
        "stock": {
          "q": 34
        }
      }
    },
    "price": "₱2603",
    "images": [
      "images/products/placeholder.svg"
    ],
    "sizes": [],
    "name": "Warm Pile Jacket",
    "stock": 34
  },
  {
    "variants": {
      "Default": {
        "stock": {
          "q": 41
        }
      }
    },
    "id": 36,
    "category2": "New Balance",
    "color": "Beige",
    "available": false,
    "category1": "Shoes",
    "category0": "MENS",
    "description": "Authentic Japanese shoes from New Balance. Limited Japan-exclusive item.",
    "name": "V-Neck Cashmere Sweater",
    "images": [
      "images/products/placeholder.svg"
    ],
    "sizes": [],
    "stock": 41,
    "price": "₱2720"
  },
  {
    "stock": 48,
    "sizes": [],
    "images": [
      "images/products/placeholder.svg"
    ],
    "name": "Flannel Check Shirt",
    "price": "₱2837",
    "id": 37,
    "variants": {
      "Default": {
        "stock": {
          "q": 48
        }
      }
    },
    "description": "Authentic Japanese clothing from Uniqlo. Limited Japan-exclusive item.",
    "category0": "MENS",
    "category1": "Clothing",
    "available": true,
    "color": "White",
    "category2": "Uniqlo"
  },
  {
    "price": "₱2954",
    "images": [
      "images/products/placeholder.svg"
    ],
    "sizes": [],
    "name": "Heattech Extra Warm Crew Neck",
    "stock": 5,
    "color": "Brown",
    "category2": "GU",
    "description": "Authentic Japanese clothing from GU. Limited Japan-exclusive item.",
    "category1": "Clothing",
    "available": true,
    "category0": "MENS",
    "id": 38,
    "variants": {
      "Default": {
        "stock": {
          "q": 5
        }
      }
    }
  },
  {
    "variants": {
      "Default": {
        "stock": {
          "q": 12
        }
      }
    },
    "id": 39,
    "category2": "Supreme",
    "color": "White",
    "category0": "MENS",
    "category1": "Clothing",
    "available": true,
    "description": "Authentic Japanese clothing from Supreme. Limited Japan-exclusive item.",
    "name": "Drake T-Shirt (Japan Drop)",
    "sizes": [],
    "images": [
      "images/products/placeholder.svg"
    ],
    "stock": 12,
    "price": "₱3071"
  },
  {
    "category2": "Nike",
    "color": "Pink",
    "category1": "Shoes",
    "available": true,
    "category0": "MENS",
    "description": "Authentic Japanese shoes from Nike. Limited Japan-exclusive item.",
    "variants": {
      "Default": {
        "stock": {
          "q": 19
        }
      }
    },
    "id": 40,
    "price": "₱3188",
    "name": "Bogo Hoodie (Japan Exclusive)",
    "images": [
      "images/products/placeholder.svg"
    ],
    "sizes": [],
    "stock": 19
  },
  {
    "id": 41,
    "variants": {
      "Default": {
        "stock": {
          "q": 26
        }
      }
    },
    "description": "Authentic Japanese shoes from Adidas. Limited Japan-exclusive item.",
    "available": true,
    "category1": "Shoes",
    "category0": "MENS",
    "color": "Pink",
    "category2": "Adidas",
    "stock": 26,
    "images": [
      "images/products/placeholder.svg"
    ],
    "sizes": [],
    "name": "PLEATED Skirt",
    "price": "₱3305"
  },
  {
    "price": "₱3422",
    "stock": 33,
    "images": [
      "images/products/placeholder.svg"
    ],
    "sizes": [],
    "name": "Mini Flare Skirt (Japan Exclusive)",
    "description": "Authentic Japanese clothing from Uniqlo. Limited Japan-exclusive item.",
    "category0": "MENS",
    "category1": "Clothing",
    "available": true,
    "color": "Lavender",
    "category2": "Uniqlo",
    "id": 42,
    "variants": {
      "Default": {
        "stock": {
          "q": 33
        }
      }
    }
  },
  {
    "stock": 40,
    "name": "Frill Tucked Blouse",
    "images": [
      "images/products/placeholder.svg"
    ],
    "sizes": [],
    "price": "₱3539",
    "variants": {
      "Default": {
        "stock": {
          "q": 40
        }
      }
    },
    "id": 43,
    "category1": "Clothing",
    "available": true,
    "category0": "MENS",
    "description": "Authentic Japanese clothing from GU. Limited Japan-exclusive item.",
    "category2": "GU",
    "color": "Black"
  },
  {
    "stock": 47,
    "sizes": [],
    "images": [
      "images/products/placeholder.svg"
    ],
    "name": "Wool Blend Coat",
    "price": "₱3656",
    "id": 44,
    "variants": {
      "Default": {
        "stock": {
          "q": 47
        }
      }
    },
    "description": "Authentic Japanese cosmetics from Shiseido. Limited Japan-exclusive item.",
    "category0": "WOMENS",
    "available": true,
    "category1": "Cosmetics",
    "color": "",
    "category2": "Shiseido"
  },
  {
    "stock": 4,
    "name": "Wide Tuck Pants",
    "sizes": [],
    "images": [
      "images/products/placeholder.svg"
    ],
    "price": "₱3773",
    "variants": {
      "Default": {
        "stock": {
          "q": 4
        }
      }
    },
    "id": 45,
    "category0": "WOMENS",
    "category1": "Cosmetics",
    "available": true,
    "description": "Authentic Japanese cosmetics from SK-II. Limited Japan-exclusive item.",
    "category2": "SK-II",
    "color": ""
  },
  {
    "id": 46,
    "variants": {
      "Default": {
        "stock": {
          "q": 11
        }
      }
    },
    "color": "Black",
    "category2": "G-Shock",
    "description": "Authentic Japanese accessories from G-Shock. Limited Japan-exclusive item.",
    "category0": "MENS",
    "available": false,
    "category1": "Accessories",
    "sizes": [],
    "images": [
      "images/products/placeholder.svg"
    ],
    "name": "Skincare Set (3-Piece)",
    "stock": 11,
    "price": "₱3890"
  },
  {
    "price": "₱4007",
    "images": [
      "images/products/placeholder.svg"
    ],
    "sizes": [],
    "name": "UV Sunscreen SPF50+",
    "stock": 18,
    "color": "Silver",
    "category2": "Lily Brown",
    "description": "Authentic Japanese accessories from Lily Brown. Limited Japan-exclusive item.",
    "category0": "MENS",
    "category1": "Accessories",
    "available": true,
    "id": 47,
    "variants": {
      "Default": {
        "stock": {
          "q": 18
        }
      }
    }
  },
  {
    "sizes": [],
    "images": [
      "images/products/placeholder.svg"
    ],
    "name": "Facial Cleansing Oil",
    "stock": 25,
    "price": "₱4124",
    "id": 48,
    "variants": {
      "Default": {
        "stock": {
          "q": 25
        }
      }
    },
    "color": "Grey",
    "category2": "WTAPS",
    "description": "Authentic Japanese clothing from WTAPS. Limited Japan-exclusive item.",
    "category1": "Clothing",
    "available": true,
    "category0": "MENS"
  },
  {
    "stock": 32,
    "name": "Moisturizing Lotion",
    "images": [
      "images/products/placeholder.svg"
    ],
    "sizes": [],
    "price": "₱4241",
    "variants": {
      "Default": {
        "stock": {
          "q": 32
        }
      }
    },
    "id": 49,
    "category1": "Clothing",
    "available": true,
    "category0": "MENS",
    "description": "Authentic Japanese clothing from Undercover. Limited Japan-exclusive item.",
    "category2": "Undercover",
    "color": "Black"
  },
  {
    "price": "₱4358",
    "stock": 39,
    "images": [
      "images/products/placeholder.svg"
    ],
    "sizes": [],
    "name": "Eye Cream (Japan Exclusive)",
    "description": "Authentic Japanese cosmetics from Canmake. Limited Japan-exclusive item.",
    "category1": "Cosmetics",
    "available": true,
    "category0": "WOMENS",
    "color": "",
    "category2": "Canmake",
    "id": 50,
    "variants": {
      "Default": {
        "stock": {
          "q": 39
        }
      }
    }
  },
  {
    "variants": {
      "Default": {
        "stock": {
          "q": 46
        }
      }
    },
    "id": 51,
    "category1": "Cosmetics",
    "available": true,
    "category0": "WOMENS",
    "description": "Authentic Japanese cosmetics from Kiss Me. Limited Japan-exclusive item.",
    "category2": "Kiss Me",
    "color": "",
    "stock": 46,
    "name": "DW-5600 Classic",
    "images": [
      "images/products/placeholder.svg"
    ],
    "sizes": [],
    "price": "₱4475"
  },
  {
    "price": "₱4592",
    "stock": 3,
    "name": "GA-2100 (Japan Exclusive)",
    "images": [
      "images/products/placeholder.svg"
    ],
    "sizes": [],
    "category0": "MENS",
    "category1": "Shoes",
    "available": true,
    "description": "Authentic Japanese shoes from Nike. Limited Japan-exclusive item.",
    "category2": "Nike",
    "color": "White",
    "variants": {
      "Default": {
        "stock": {
          "q": 3
        }
      }
    },
    "id": 52
  },
  {
    "price": "₱4709",
    "stock": 10,
    "images": [
      "images/products/placeholder.svg"
    ],
    "sizes": [],
    "name": "MTG-B2000",
    "description": "Authentic Japanese shoes from Adidas. Limited Japan-exclusive item.",
    "category0": "MENS",
    "category1": "Shoes",
    "available": true,
    "color": "White",
    "category2": "Adidas",
    "id": 53,
    "variants": {
      "Default": {
        "stock": {
          "q": 10
        }
      }
    }
  },
  {
    "id": 54,
    "variants": {
      "Default": {
        "stock": {
          "q": 17
        }
      }
    },
    "description": "Authentic Japanese shoes from New Balance. Limited Japan-exclusive item.",
    "available": true,
    "category1": "Shoes",
    "category0": "MENS",
    "color": "Beige",
    "category2": "New Balance",
    "stock": 17,
    "sizes": [],
    "images": [
      "images/products/placeholder.svg"
    ],
    "name": "GMW-B5000",
    "price": "₱4826"
  },
  {
    "price": "₱4943",
    "stock": 24,
    "name": "DW-6900 Japan Limited",
    "sizes": [],
    "images": [
      "images/products/placeholder.svg"
    ],
    "available": true,
    "category1": "Clothing",
    "category0": "MENS",
    "description": "Authentic Japanese clothing from Uniqlo. Limited Japan-exclusive item.",
    "category2": "Uniqlo",
    "color": "Olive",
    "variants": {
      "Default": {
        "stock": {
          "q": 24
        }
      }
    },
    "id": 55
  },
  {
    "color": "Black",
    "category2": "GU",
    "description": "Authentic Japanese clothing from GU. Limited Japan-exclusive item.",
    "category1": "Clothing",
    "available": false,
    "category0": "MENS",
    "id": 56,
    "variants": {
      "Default": {
        "stock": {
          "q": 31
        }
      }
    },
    "price": "₱5060",
    "images": [
      "images/products/placeholder.svg"
    ],
    "sizes": [],
    "name": "Pouch Set (3-Piece)",
    "stock": 31
  },
  {
    "variants": {
      "Default": {
        "stock": {
          "q": 38
        }
      }
    },
    "id": 57,
    "category2": "Supreme",
    "color": "White",
    "category0": "MENS",
    "available": true,
    "category1": "Clothing",
    "description": "Authentic Japanese clothing from Supreme. Limited Japan-exclusive item.",
    "name": "Canvas Shoulder Bag",
    "sizes": [],
    "images": [
      "images/products/placeholder.svg"
    ],
    "stock": 38,
    "price": "₱5177"
  },
  {
    "price": "₱5294",
    "stock": 45,
    "images": [
      "images/products/placeholder.svg"
    ],
    "sizes": [],
    "name": "Knitted Beanie",
    "description": "Authentic Japanese shoes from Nike. Limited Japan-exclusive item.",
    "category0": "MENS",
    "category1": "Shoes",
    "available": true,
    "color": "Pink",
    "category2": "Nike",
    "id": 58,
    "variants": {
      "Default": {
        "stock": {
          "q": 45
        }
      }
    }
  },
  {
    "stock": 2,
    "name": "Leather Gloves",
    "sizes": [],
    "images": [
      "images/products/placeholder.svg"
    ],
    "price": "₱5411",
    "variants": {
      "Default": {
        "stock": {
          "q": 2
        }
      }
    },
    "id": 59,
    "category0": "MENS",
    "category1": "Shoes",
    "available": true,
    "description": "Authentic Japanese shoes from Adidas. Limited Japan-exclusive item.",
    "category2": "Adidas",
    "color": "Pink"
  },
  {
    "price": "₱408",
    "stock": 9,
    "sizes": [],
    "images": [
      "images/products/placeholder.svg"
    ],
    "name": "Silk Scarf (Japan Exclusive)",
    "description": "Authentic Japanese clothing from Uniqlo. Limited Japan-exclusive item.",
    "category0": "MENS",
    "category1": "Clothing",
    "available": true,
    "color": "White",
    "category2": "Uniqlo",
    "id": 60,
    "variants": {
      "Default": {
        "stock": {
          "q": 9
        }
      }
    }
  },
  {
    "available": true,
    "category1": "Clothing",
    "category0": "MENS",
    "description": "Authentic Japanese clothing from GU. Limited Japan-exclusive item.",
    "category2": "GU",
    "color": "Pink",
    "variants": {
      "Default": {
        "stock": {
          "q": 16
        }
      }
    },
    "id": 61,
    "price": "₱525",
    "stock": 16,
    "name": "Sweatpants (Japan Drop)",
    "images": [
      "images/products/placeholder.svg"
    ],
    "sizes": []
  },
  {
    "description": "Authentic Japanese cosmetics from Shiseido. Limited Japan-exclusive item.",
    "category0": "WOMENS",
    "available": true,
    "category1": "Cosmetics",
    "color": "",
    "category2": "Shiseido",
    "id": 62,
    "variants": {
      "Default": {
        "stock": {
          "q": 23
        }
      }
    },
    "price": "₱642",
    "stock": 23,
    "images": [
      "images/products/placeholder.svg"
    ],
    "sizes": [],
    "name": "Cargo Pants"
  },
  {
    "variants": {
      "Default": {
        "stock": {
          "q": 30
        }
      }
    },
    "id": 63,
    "category1": "Cosmetics",
    "available": true,
    "category0": "WOMENS",
    "description": "Authentic Japanese cosmetics from SK-II. Limited Japan-exclusive item.",
    "category2": "SK-II",
    "color": "",
    "stock": 30,
    "name": "Denim Jacket (Made in Japan)",
    "sizes": [],
    "images": [
      "images/products/placeholder.svg"
    ],
    "price": "₱759"
  },
  {
    "id": 64,
    "variants": {
      "Default": {
        "stock": {
          "q": 37
        }
      }
    },
    "description": "Authentic Japanese accessories from G-Shock. Limited Japan-exclusive item.",
    "category0": "MENS",
    "category1": "Accessories",
    "available": true,
    "color": "Green",
    "category2": "G-Shock",
    "stock": 37,
    "images": [
      "images/products/placeholder.svg"
    ],
    "sizes": [],
    "name": "Ripstop Shorts",
    "price": "₱876"
  },
  {
    "stock": 44,
    "images": [
      "images/products/placeholder.svg"
    ],
    "sizes": [],
    "name": "Military Shirt",
    "price": "₱993",
    "id": 65,
    "variants": {
      "Default": {
        "stock": {
          "q": 44
        }
      }
    },
    "description": "Authentic Japanese accessories from Lily Brown. Limited Japan-exclusive item.",
    "available": true,
    "category1": "Accessories",
    "category0": "MENS",
    "color": "Silver",
    "category2": "Lily Brown"
  },
  {
    "description": "Authentic Japanese clothing from WTAPS. Limited Japan-exclusive item.",
    "available": false,
    "category1": "Clothing",
    "category0": "MENS",
    "color": "Grey",
    "category2": "WTAPS",
    "id": 66,
    "variants": {
      "Default": {
        "stock": {
          "q": 1
        }
      }
    },
    "price": "₱1110",
    "stock": 1,
    "images": [
      "images/products/placeholder.svg"
    ],
    "sizes": [],
    "name": "Hooded Down Parka"
  },
  {
    "stock": 8,
    "name": "Merino Wool Crew Neck",
    "sizes": [],
    "images": [
      "images/products/placeholder.svg"
    ],
    "price": "₱1227",
    "variants": {
      "Default": {
        "stock": {
          "q": 8
        }
      }
    },
    "id": 67,
    "available": true,
    "category1": "Clothing",
    "category0": "MENS",
    "description": "Authentic Japanese clothing from Undercover. Limited Japan-exclusive item.",
    "category2": "Undercover",
    "color": "Black"
  },
  {
    "category2": "Canmake",
    "color": "",
    "category1": "Cosmetics",
    "available": true,
    "category0": "WOMENS",
    "description": "Authentic Japanese cosmetics from Canmake. Limited Japan-exclusive item.",
    "variants": {
      "Default": {
        "stock": {
          "q": 15
        }
      }
    },
    "id": 68,
    "price": "₱1344",
    "name": "Crew Socks (5-Pack)",
    "images": [
      "images/products/placeholder.svg"
    ],
    "sizes": [],
    "stock": 15
  },
  {
    "color": "",
    "category2": "Kiss Me",
    "description": "Authentic Japanese cosmetics from Kiss Me. Limited Japan-exclusive item.",
    "category0": "WOMENS",
    "category1": "Cosmetics",
    "available": true,
    "id": 69,
    "variants": {
      "Default": {
        "stock": {
          "q": 22
        }
      }
    },
    "price": "₱1461",
    "images": [
      "images/products/placeholder.svg"
    ],
    "sizes": [],
    "name": "Cotton Linen Shirt",
    "stock": 22
  },
  {
    "images": [
      "images/products/placeholder.svg"
    ],
    "sizes": [],
    "name": "Easy Shorts",
    "stock": 29,
    "price": "₱1578",
    "id": 70,
    "variants": {
      "Default": {
        "stock": {
          "q": 29
        }
      }
    },
    "color": "Green",
    "category2": "Nike",
    "description": "Authentic Japanese shoes from Nike. Limited Japan-exclusive item.",
    "category0": "MENS",
    "available": true,
    "category1": "Shoes"
  },
  {
    "description": "Authentic Japanese shoes from Adidas. Limited Japan-exclusive item.",
    "category0": "MENS",
    "category1": "Shoes",
    "available": true,
    "color": "White",
    "category2": "Adidas",
    "id": 71,
    "variants": {
      "Default": {
        "stock": {
          "q": 36
        }
      }
    },
    "price": "₱1695",
    "stock": 36,
    "sizes": [],
    "images": [
      "images/products/placeholder.svg"
    ],
    "name": "Longchamp Le Pliage"
  },
  {
    "images": [
      "images/products/placeholder.svg"
    ],
    "sizes": [],
    "name": "Anello Backpack",
    "stock": 43,
    "price": "₱1812",
    "id": 72,
    "variants": {
      "Default": {
        "stock": {
          "q": 43
        }
      }
    },
    "color": "Beige",
    "category2": "New Balance",
    "description": "Authentic Japanese shoes from New Balance. Limited Japan-exclusive item.",
    "available": true,
    "category1": "Shoes",
    "category0": "MENS"
  },
  {
    "stock": 50,
    "sizes": [],
    "images": [
      "images/products/placeholder.svg"
    ],
    "name": "Porter Tanker 2-Way",
    "price": "₱1929",
    "id": 73,
    "variants": {
      "Default": {
        "stock": {
          "q": 50
        }
      }
    },
    "description": "Authentic Japanese clothing from Uniqlo. Limited Japan-exclusive item.",
    "category0": "MENS",
    "category1": "Clothing",
    "available": true,
    "color": "Navy",
    "category2": "Uniqlo"
  },
  {
    "stock": 7,
    "images": [
      "images/products/placeholder.svg"
    ],
    "sizes": [],
    "name": "Muji Labo Coat",
    "price": "₱2046",
    "id": 74,
    "variants": {
      "Default": {
        "stock": {
          "q": 7
        }
      }
    },
    "description": "Authentic Japanese clothing from GU. Limited Japan-exclusive item.",
    "category1": "Clothing",
    "available": true,
    "category0": "MENS",
    "color": "Brown",
    "category2": "GU"
  },
  {
    "price": "₱2163",
    "stock": 14,
    "sizes": [],
    "images": [
      "images/products/placeholder.svg"
    ],
    "name": "Snow Peak Down Vest",
    "description": "Authentic Japanese clothing from Supreme. Limited Japan-exclusive item.",
    "category1": "Clothing",
    "available": true,
    "category0": "MENS",
    "color": "White",
    "category2": "Supreme",
    "id": 75,
    "variants": {
      "Default": {
        "stock": {
          "q": 14
        }
      }
    }
  },
  {
    "id": 76,
    "variants": {
      "Default": {
        "stock": {
          "q": 21
        }
      }
    },
    "description": "Authentic Japanese shoes from Nike. Limited Japan-exclusive item.",
    "available": false,
    "category1": "Shoes",
    "category0": "MENS",
    "color": "Pink",
    "category2": "Nike",
    "stock": 21,
    "images": [
      "images/products/placeholder.svg"
    ],
    "sizes": [],
    "name": "24H Cosme Lip Balm",
    "price": "₱2280"
  },
  {
    "category1": "Shoes",
    "available": true,
    "category0": "MENS",
    "description": "Authentic Japanese shoes from Adidas. Limited Japan-exclusive item.",
    "category2": "Adidas",
    "color": "Pink",
    "variants": {
      "Default": {
        "stock": {
          "q": 28
        }
      }
    },
    "id": 77,
    "price": "₱2397",
    "stock": 28,
    "name": "Fujiko Lip Oil",
    "images": [
      "images/products/placeholder.svg"
    ],
    "sizes": []
  },
  {
    "variants": {
      "Default": {
        "stock": {
          "q": 35
        }
      }
    },
    "id": 78,
    "category2": "Uniqlo",
    "color": "Lavender",
    "category0": "MENS",
    "available": true,
    "category1": "Clothing",
    "description": "Authentic Japanese clothing from Uniqlo. Limited Japan-exclusive item.",
    "name": "Excel Eyebrow Powder",
    "images": [
      "images/products/placeholder.svg"
    ],
    "sizes": [],
    "stock": 35,
    "price": "₱2514"
  },
  {
    "price": "₱2631",
    "name": "Kate Liquid Eyeliner",
    "images": [
      "images/products/placeholder.svg"
    ],
    "sizes": [],
    "stock": 42,
    "category2": "GU",
    "color": "Black",
    "category1": "Clothing",
    "available": true,
    "category0": "MENS",
    "description": "Authentic Japanese clothing from GU. Limited Japan-exclusive item.",
    "variants": {
      "Default": {
        "stock": {
          "q": 42
        }
      }
    },
    "id": 79
  },
  {
    "id": 80,
    "variants": {
      "Default": {
        "stock": {
          "q": 49
        }
      }
    },
    "color": "",
    "category2": "Shiseido",
    "description": "Authentic Japanese cosmetics from Shiseido. Limited Japan-exclusive item.",
    "available": true,
    "category1": "Cosmetics",
    "category0": "WOMENS",
    "sizes": [],
    "images": [
      "images/products/placeholder.svg"
    ],
    "name": "Majolica Majorca Mascara",
    "stock": 49,
    "price": "₱2748"
  },
  {
    "images": [
      "images/products/placeholder.svg"
    ],
    "sizes": [],
    "name": "Nylon Puffer Jacket",
    "stock": 6,
    "price": "₱2865",
    "id": 81,
    "variants": {
      "Default": {
        "stock": {
          "q": 6
        }
      }
    },
    "color": "",
    "category2": "SK-II",
    "description": "Authentic Japanese cosmetics from SK-II. Limited Japan-exclusive item.",
    "available": true,
    "category1": "Cosmetics",
    "category0": "WOMENS"
  },
  {
    "price": "₱2982",
    "images": [
      "images/products/placeholder.svg"
    ],
    "sizes": [],
    "name": "Ribbed Knit Top",
    "stock": 13,
    "color": "White",
    "category2": "G-Shock",
    "description": "Authentic Japanese accessories from G-Shock. Limited Japan-exclusive item.",
    "category1": "Accessories",
    "available": true,
    "category0": "MENS",
    "id": 82,
    "variants": {
      "Default": {
        "stock": {
          "q": 13
        }
      }
    }
  },
  {
    "color": "Silver",
    "category2": "Lily Brown",
    "description": "Authentic Japanese accessories from Lily Brown. Limited Japan-exclusive item.",
    "category0": "MENS",
    "available": true,
    "category1": "Accessories",
    "id": 83,
    "variants": {
      "Default": {
        "stock": {
          "q": 20
        }
      }
    },
    "price": "₱3099",
    "sizes": [],
    "images": [
      "images/products/placeholder.svg"
    ],
    "name": "Midi Wrap Skirt",
    "stock": 20
  },
  {
    "price": "₱3216",
    "stock": 27,
    "sizes": [],
    "images": [
      "images/products/placeholder.svg"
    ],
    "name": "Wool Flared Pants",
    "description": "Authentic Japanese clothing from WTAPS. Limited Japan-exclusive item.",
    "category1": "Clothing",
    "available": true,
    "category0": "MENS",
    "color": "Grey",
    "category2": "WTAPS",
    "id": 84,
    "variants": {
      "Default": {
        "stock": {
          "q": 27
        }
      }
    }
  },
  {
    "color": "Black",
    "category2": "Undercover",
    "description": "Authentic Japanese clothing from Undercover. Limited Japan-exclusive item.",
    "category1": "Clothing",
    "available": true,
    "category0": "MENS",
    "id": 85,
    "variants": {
      "Default": {
        "stock": {
          "q": 34
        }
      }
    },
    "price": "₱3333",
    "images": [
      "images/products/placeholder.svg"
    ],
    "sizes": [],
    "name": "Belted Trench Coat",
    "stock": 34
  },
  {
    "stock": 41,
    "sizes": [],
    "images": [
      "images/products/placeholder.svg"
    ],
    "name": "Patchwork Denim Jacket",
    "price": "₱3450",
    "id": 86,
    "variants": {
      "Default": {
        "stock": {
          "q": 41
        }
      }
    },
    "description": "Authentic Japanese cosmetics from Canmake. Limited Japan-exclusive item.",
    "category0": "WOMENS",
    "available": false,
    "category1": "Cosmetics",
    "color": "",
    "category2": "Canmake"
  },
  {
    "id": 87,
    "variants": {
      "Default": {
        "stock": {
          "q": 48
        }
      }
    },
    "description": "Authentic Japanese cosmetics from Kiss Me. Limited Japan-exclusive item.",
    "available": true,
    "category1": "Cosmetics",
    "category0": "WOMENS",
    "color": "",
    "category2": "Kiss Me",
    "stock": 48,
    "images": [
      "images/products/placeholder.svg"
    ],
    "sizes": [],
    "name": "Oversized Hoodie (Japan Exclusive)",
    "price": "₱3567"
  },
  {
    "stock": 5,
    "images": [
      "images/products/placeholder.svg"
    ],
    "sizes": [],
    "name": "Carpenter Pants",
    "price": "₱3684",
    "id": 88,
    "variants": {
      "Default": {
        "stock": {
          "q": 5
        }
      }
    },
    "description": "Authentic Japanese shoes from Nike. Limited Japan-exclusive item.",
    "category0": "MENS",
    "available": true,
    "category1": "Shoes",
    "color": "Red",
    "category2": "Nike"
  },
  {
    "price": "₱3801",
    "images": [
      "images/products/placeholder.svg"
    ],
    "sizes": [],
    "name": "Graphic T-Shirt",
    "stock": 12,
    "color": "White",
    "category2": "Adidas",
    "description": "Authentic Japanese shoes from Adidas. Limited Japan-exclusive item.",
    "category0": "MENS",
    "available": true,
    "category1": "Shoes",
    "id": 89,
    "variants": {
      "Default": {
        "stock": {
          "q": 12
        }
      }
    }
  },
  {
    "stock": 19,
    "images": [
      "images/products/placeholder.svg"
    ],
    "sizes": [],
    "name": "Work Jacket",
    "price": "₱3918",
    "id": 90,
    "variants": {
      "Default": {
        "stock": {
          "q": 19
        }
      }
    },
    "description": "Authentic Japanese shoes from New Balance. Limited Japan-exclusive item.",
    "category0": "MENS",
    "available": true,
    "category1": "Shoes",
    "color": "Beige",
    "category2": "New Balance"
  },
  {
    "id": 91,
    "variants": {
      "Default": {
        "stock": {
          "q": 26
        }
      }
    },
    "description": "Authentic Japanese clothing from Uniqlo. Limited Japan-exclusive item.",
    "available": true,
    "category1": "Clothing",
    "category0": "MENS",
    "color": "Black",
    "category2": "Uniqlo",
    "stock": 26,
    "images": [
      "images/products/placeholder.svg"
    ],
    "sizes": [],
    "name": "Kyoto Matcha Set (Limited)",
    "price": "₱4035"
  },
  {
    "name": "Sake Tasting Set",
    "images": [
      "images/products/placeholder.svg"
    ],
    "sizes": [],
    "stock": 33,
    "price": "₱4152",
    "variants": {
      "Default": {
        "stock": {
          "q": 33
        }
      }
    },
    "id": 92,
    "category2": "GU",
    "color": "Black",
    "available": true,
    "category1": "Clothing",
    "category0": "MENS",
    "description": "Authentic Japanese clothing from GU. Limited Japan-exclusive item."
  },
  {
    "name": "Japanese Snack Box (20pc)",
    "sizes": [],
    "images": [
      "images/products/placeholder.svg"
    ],
    "stock": 40,
    "price": "₱4269",
    "variants": {
      "Default": {
        "stock": {
          "q": 40
        }
      }
    },
    "id": 93,
    "category2": "Supreme",
    "color": "White",
    "category1": "Clothing",
    "available": true,
    "category0": "MENS",
    "description": "Authentic Japanese clothing from Supreme. Limited Japan-exclusive item."
  },
  {
    "images": [
      "images/products/placeholder.svg"
    ],
    "sizes": [],
    "name": "Premium Gyokuro Tea",
    "stock": 47,
    "price": "₱4386",
    "id": 94,
    "variants": {
      "Default": {
        "stock": {
          "q": 47
        }
      }
    },
    "color": "Pink",
    "category2": "Nike",
    "description": "Authentic Japanese shoes from Nike. Limited Japan-exclusive item.",
    "category1": "Shoes",
    "available": true,
    "category0": "MENS"
  },
  {
    "images": [
      "images/products/placeholder.svg"
    ],
    "sizes": [],
    "name": "Dashi Stock Set",
    "stock": 4,
    "price": "₱4503",
    "id": 95,
    "variants": {
      "Default": {
        "stock": {
          "q": 4
        }
      }
    },
    "color": "Pink",
    "category2": "Adidas",
    "description": "Authentic Japanese shoes from Adidas. Limited Japan-exclusive item.",
    "available": true,
    "category1": "Shoes",
    "category0": "MENS"
  },
  {
    "variants": {
      "Default": {
        "stock": {
          "q": 11
        }
      }
    },
    "id": 96,
    "category0": "MENS",
    "available": false,
    "category1": "Clothing",
    "description": "Authentic Japanese clothing from Uniqlo. Limited Japan-exclusive item.",
    "category2": "Uniqlo",
    "color": "White",
    "stock": 11,
    "name": "Champion Reverse Weave Hoodie",
    "images": [
      "images/products/placeholder.svg"
    ],
    "sizes": [],
    "price": "₱4620"
  },
  {
    "price": "₱4737",
    "name": "Karrimor Shoulder Bag",
    "sizes": [],
    "images": [
      "images/products/placeholder.svg"
    ],
    "stock": 18,
    "category2": "GU",
    "color": "Pink",
    "category0": "MENS",
    "category1": "Clothing",
    "available": true,
    "description": "Authentic Japanese clothing from GU. Limited Japan-exclusive item.",
    "variants": {
      "Default": {
        "stock": {
          "q": 18
        }
      }
    },
    "id": 97
  },
  {
    "sizes": [],
    "images": [
      "images/products/placeholder.svg"
    ],
    "name": "Snow Peak Titanium Mug",
    "stock": 25,
    "price": "₱4854",
    "id": 98,
    "variants": {
      "Default": {
        "stock": {
          "q": 25
        }
      }
    },
    "color": "",
    "category2": "Shiseido",
    "description": "Authentic Japanese cosmetics from Shiseido. Limited Japan-exclusive item.",
    "category0": "WOMENS",
    "category1": "Cosmetics",
    "available": true
  },
  {
    "price": "₱4971",
    "name": "Mont-bell Down Jacket",
    "images": [
      "images/products/placeholder.svg"
    ],
    "sizes": [],
    "stock": 32,
    "category2": "SK-II",
    "color": "",
    "category0": "WOMENS",
    "available": true,
    "category1": "Cosmetics",
    "description": "Authentic Japanese cosmetics from SK-II. Limited Japan-exclusive item.",
    "variants": {
      "Default": {
        "stock": {
          "q": 32
        }
      }
    },
    "id": 99
  },
  {
    "variants": {
      "Default": {
        "stock": {
          "q": 39
        }
      }
    },
    "id": 100,
    "category2": "G-Shock",
    "color": "Blue",
    "category0": "MENS",
    "category1": "Accessories",
    "available": true,
    "description": "Authentic Japanese accessories from G-Shock. Limited Japan-exclusive item.",
    "name": "Asics Tiger Me... (Japan Exclusive)",
    "images": [
      "images/products/placeholder.svg"
    ],
    "sizes": [],
    "stock": 39,
    "price": "₱5088"
  },
  {
    "color": "Silver",
    "category2": "Lily Brown",
    "description": "Authentic Japanese accessories from Lily Brown. Limited Japan-exclusive item.",
    "category1": "Accessories",
    "available": true,
    "category0": "MENS",
    "id": 101,
    "variants": {
      "Default": {
        "stock": {
          "q": 46
        }
      }
    },
    "price": "₱5205",
    "sizes": [],
    "images": [
      "images/products/placeholder.svg"
    ],
    "name": "Air Max 97 (Japan Exclusive)",
    "stock": 46
  },
  {
    "variants": {
      "Default": {
        "stock": {
          "q": 3
        }
      }
    },
    "id": 102,
    "category2": "WTAPS",
    "color": "Grey",
    "category0": "MENS",
    "available": true,
    "category1": "Clothing",
    "description": "Authentic Japanese clothing from WTAPS. Limited Japan-exclusive item.",
    "name": "Dunk High Retro",
    "images": [
      "images/products/placeholder.svg"
    ],
    "sizes": [],
    "stock": 3,
    "price": "₱5322"
  },
  {
    "id": 103,
    "variants": {
      "Default": {
        "stock": {
          "q": 10
        }
      }
    },
    "color": "Black",
    "category2": "Undercover",
    "description": "Authentic Japanese clothing from Undercover. Limited Japan-exclusive item.",
    "category0": "MENS",
    "available": true,
    "category1": "Clothing",
    "images": [
      "images/products/placeholder.svg"
    ],
    "sizes": [],
    "name": "Air Jordan 1 Low",
    "stock": 10,
    "price": "₱5439"
  },
  {
    "price": "₱436",
    "images": [
      "images/products/placeholder.svg"
    ],
    "sizes": [],
    "name": "Blazer Mid '77",
    "stock": 17,
    "color": "",
    "category2": "Canmake",
    "description": "Authentic Japanese cosmetics from Canmake. Limited Japan-exclusive item.",
    "category0": "WOMENS",
    "available": true,
    "category1": "Cosmetics",
    "id": 104,
    "variants": {
      "Default": {
        "stock": {
          "q": 17
        }
      }
    }
  },
  {
    "variants": {
      "Default": {
        "stock": {
          "q": 24
        }
      }
    },
    "id": 105,
    "category2": "Kiss Me",
    "color": "",
    "available": true,
    "category1": "Cosmetics",
    "category0": "WOMENS",
    "description": "Authentic Japanese cosmetics from Kiss Me. Limited Japan-exclusive item.",
    "name": "Air Force 1 Mid",
    "images": [
      "images/products/placeholder.svg"
    ],
    "sizes": [],
    "stock": 24,
    "price": "₱553"
  },
  {
    "name": "Ultraboost 22",
    "images": [
      "images/products/placeholder.svg"
    ],
    "sizes": [],
    "stock": 31,
    "price": "₱670",
    "variants": {
      "Default": {
        "stock": {
          "q": 31
        }
      }
    },
    "id": 106,
    "category2": "Nike",
    "color": "Black",
    "category1": "Shoes",
    "available": false,
    "category0": "MENS",
    "description": "Authentic Japanese shoes from Nike. Limited Japan-exclusive item."
  },
  {
    "name": "NMD_R1 Primeknit",
    "images": [
      "images/products/placeholder.svg"
    ],
    "sizes": [],
    "stock": 38,
    "price": "₱787",
    "variants": {
      "Default": {
        "stock": {
          "q": 38
        }
      }
    },
    "id": 107,
    "category2": "Adidas",
    "color": "White",
    "category0": "MENS",
    "available": true,
    "category1": "Shoes",
    "description": "Authentic Japanese shoes from Adidas. Limited Japan-exclusive item."
  },
  {
    "id": 108,
    "variants": {
      "Default": {
        "stock": {
          "q": 45
        }
      }
    },
    "description": "Authentic Japanese shoes from New Balance. Limited Japan-exclusive item.",
    "category0": "MENS",
    "category1": "Shoes",
    "available": true,
    "color": "Beige",
    "category2": "New Balance",
    "stock": 45,
    "sizes": [],
    "images": [
      "images/products/placeholder.svg"
    ],
    "name": "Superstar (Japan Edition)",
    "price": "₱904"
  },
  {
    "id": 109,
    "variants": {
      "Default": {
        "stock": {
          "q": 2
        }
      }
    },
    "color": "Beige",
    "category2": "Uniqlo",
    "description": "Authentic Japanese clothing from Uniqlo. Limited Japan-exclusive item.",
    "category0": "MENS",
    "category1": "Clothing",
    "available": true,
    "images": [
      "images/products/placeholder.svg"
    ],
    "sizes": [],
    "name": "Gazelle (Made in Japan)",
    "stock": 2,
    "price": "₱1021"
  },
  {
    "variants": {
      "Default": {
        "stock": {
          "q": 9
        }
      }
    },
    "id": 110,
    "category2": "GU",
    "color": "Brown",
    "available": true,
    "category1": "Clothing",
    "category0": "MENS",
    "description": "Authentic Japanese clothing from GU. Limited Japan-exclusive item.",
    "name": "Forum Low",
    "sizes": [],
    "images": [
      "images/products/placeholder.svg"
    ],
    "stock": 9,
    "price": "₱1138"
  },
  {
    "stock": 16,
    "name": "550 (Japan Exclusive)",
    "images": [
      "images/products/placeholder.svg"
    ],
    "sizes": [],
    "price": "₱1255",
    "variants": {
      "Default": {
        "stock": {
          "q": 16
        }
      }
    },
    "id": 111,
    "category0": "MENS",
    "available": true,
    "category1": "Clothing",
    "description": "Authentic Japanese clothing from Supreme. Limited Japan-exclusive item.",
    "category2": "Supreme",
    "color": "White"
  },
  {
    "color": "Pink",
    "category2": "Nike",
    "description": "Authentic Japanese shoes from Nike. Limited Japan-exclusive item.",
    "category1": "Shoes",
    "available": true,
    "category0": "MENS",
    "id": 112,
    "variants": {
      "Default": {
        "stock": {
          "q": 23
        }
      }
    },
    "price": "₱1372",
    "sizes": [],
    "images": [
      "images/products/placeholder.svg"
    ],
    "name": "574 Classic",
    "stock": 23
  },
  {
    "category2": "Adidas",
    "color": "Pink",
    "category0": "MENS",
    "available": true,
    "category1": "Shoes",
    "description": "Authentic Japanese shoes from Adidas. Limited Japan-exclusive item.",
    "variants": {
      "Default": {
        "stock": {
          "q": 30
        }
      }
    },
    "id": 113,
    "price": "₱1489",
    "name": "990v5 Made in Japan",
    "sizes": [],
    "images": [
      "images/products/placeholder.svg"
    ],
    "stock": 30
  },
  {
    "price": "₱1606",
    "name": "U9060",
    "sizes": [],
    "images": [
      "images/products/placeholder.svg"
    ],
    "stock": 37,
    "category2": "Uniqlo",
    "color": "Lavender",
    "category1": "Clothing",
    "available": true,
    "category0": "MENS",
    "description": "Authentic Japanese clothing from Uniqlo. Limited Japan-exclusive item.",
    "variants": {
      "Default": {
        "stock": {
          "q": 37
        }
      }
    },
    "id": 114
  },
  {
    "available": true,
    "category1": "Clothing",
    "category0": "MENS",
    "description": "Authentic Japanese clothing from GU. Limited Japan-exclusive item.",
    "category2": "GU",
    "color": "Black",
    "variants": {
      "Default": {
        "stock": {
          "q": 44
        }
      }
    },
    "id": 115,
    "price": "₱1723",
    "stock": 44,
    "name": "Bape STA Low",
    "images": [
      "images/products/placeholder.svg"
    ],
    "sizes": []
  }
]